aiger_coins/__init__.py
aiger_coins/infer.py
aiger_coins/pcirc.py
py_aiger_coins-3.3.7.dist-info/LICENSE
py_aiger_coins-3.3.7.dist-info/WHEEL
py_aiger_coins-3.3.7.dist-info/METADATA
py_aiger_coins-3.3.7.dist-info/RECORD
