Metadata-Version: 2.1
Name: py-aiger-coins
Version: 3.3.7
Summary: Library for creating circuits that encode discrete distributions.
Home-page: https://github.com/mvcisback/py-aiger-coins
License: MIT
Author: Marcell Vazquez-Chanlatte
Author-email: mvc@linux.com
Requires-Python: >=3.9,<4.0
Classifier: License :: OSI Approved :: MIT License
Classifier: Programming Language :: Python :: 3
Classifier: Programming Language :: Python :: 3.10
Classifier: Programming Language :: Python :: 3.9
Provides-Extra: bdd
Provides-Extra: sat
Requires-Dist: attrs (>=22,<23)
Requires-Dist: funcy (>=1.13,<2.0)
Requires-Dist: mdd (>=0.3.4,<0.4.0); extra == "bdd"
Requires-Dist: numpy (>=1.19.4,<2.0.0); extra == "bdd"
Requires-Dist: py-aiger (>=6.1.1,<7.0.0)
Requires-Dist: py-aiger-bdd (>=3.0.0,<4.0.0); extra == "bdd"
Requires-Dist: py-aiger-bv (>=4.4.0,<5.0.0)
Requires-Dist: py-aiger-discrete (>=0.1.2,<0.2.0)
Requires-Dist: py-aiger-sat (>=3.0.4,<4.0.0); extra == "sat"
Project-URL: Repository, https://github.com/mvcisback/py-aiger-coins
